directory_constants/__init__.py
directory_constants/choices.py
directory_constants/cms.py
directory_constants/company_types.py
directory_constants/expertise.py
directory_constants/export_plan.py
directory_constants/exporting.py
directory_constants/helpers.py
directory_constants/sectors.py
directory_constants/slugs.py
directory_constants/user_roles.py
directory_constants/fixtures/countries-and-territories.json
directory_constants/fixtures/country.json
directory_constants/fixtures/countryorterritory.region.type.json
directory_constants/fixtures/dit-sector-list-legacy.json
directory_constants/fixtures/dit-sector-list.json
directory_constants/fixtures/sic.csv
directory_constants/urls/__init__.py
directory_constants/urls/domestic.py
directory_constants/urls/international.py
directory_constants/urls/magna.py
directory_constants-24.2.0.dist-info/licenses/LICENSE
directory_constants-24.2.0.dist-info/METADATA
directory_constants-24.2.0.dist-info/WHEEL
directory_constants-24.2.0.dist-info/top_level.txt
directory_constants-24.2.0.dist-info/RECORD
