Metadata-Version: 2.4
Name: directory_constants
Version: 24.2.0
Summary: Constant values shared between Directory apps.
Home-page: https://github.com/uktrade/directory-constants
Author: Department for Business and Trade
License: MIT
Classifier: Development Status :: 5 - Production/Stable
Classifier: Environment :: Web Environment
Classifier: Framework :: Django
Classifier: Framework :: Django :: 4.2
Classifier: Intended Audience :: Developers
Classifier: License :: OSI Approved :: MIT License
Classifier: Natural Language :: English
Classifier: Operating System :: OS Independent
Classifier: Programming Language :: Python :: 3.9
Classifier: Programming Language :: Python :: 3.13
Classifier: Topic :: Software Development :: Libraries :: Python Modules
License-File: LICENSE
Requires-Dist: django<=5.0,>=4.2.10
Provides-Extra: test
Requires-Dist: pytest>=3.6.0; extra == "test"
Requires-Dist: pytest-cov>=2.7.1; extra == "test"
Requires-Dist: pytest-django>=3.3.0; extra == "test"
Requires-Dist: flake8>=5.0.4; extra == "test"
Requires-Dist: twine; extra == "test"
Requires-Dist: wheel<1.0.0,>=0.31.0; extra == "test"
Requires-Dist: freezegun>=0.3.8; extra == "test"
Requires-Dist: setuptools; extra == "test"
Dynamic: author
Dynamic: classifier
Dynamic: description
Dynamic: description-content-type
Dynamic: home-page
Dynamic: license
Dynamic: license-file
Dynamic: provides-extra
Dynamic: requires-dist
Dynamic: summary
